{"title":"Start script for deploy a centOS with XFCE on Vultr","date":"2018-06-21T18:53:14.000Z","excerpt":"","slug":"helloword","comments":true,"tags":["gist"],"categories":["general programming"],"updated":"2018-06-21T23:12:49.012Z","content":"<h1 id=\"Hello-world\"><a href=\"#Hello-world\" class=\"headerlink\" title=\"Hello world\"></a>Hello world</h1><script src=\"//gist.github.com/3f8cd7eaa654f1fa2f4da7288162f96a.js?file=vultr_startup_xfce4.sh\"></script>\n","link":"http://sisyphus-deng.github.io/post/helloword"}